photocmp/__init__.py
photocmp-0.3.1.data/scripts/photocompare
photocmp-0.3.1.dist-info/LICENSE
photocmp-0.3.1.dist-info/METADATA
photocmp-0.3.1.dist-info/WHEEL
photocmp-0.3.1.dist-info/top_level.txt
photocmp-0.3.1.dist-info/RECORD
