Metadata-Version: 2.1
Name: photocmp
Version: 0.3.1
Summary: Tool and library to compare sets of images
Home-page: https://github.com/claudio-unipv/photocmp
Author: Claudio Cusano
Author-email: claudio.cusano@unipv.it
License: UNKNOWN
Platform: UNKNOWN
Classifier: Programming Language :: Python :: 3
Classifier: License :: OSI Approved :: MIT License
Classifier: Operating System :: OS Independent
Requires-Python: >=3.6
License-File: LICENSE
Requires-Dist: Pillow (>=5.1.0)
Requires-Dist: numpy (>=1.13.0)
